solvis/__init__.py
solvis/config.py
solvis/dochelper/__init__.py
solvis/dochelper/extension.py
solvis/dochelper/inherit_docstrings.py
solvis/fault_system_solution_helper.py
solvis/filter/__init__.py
solvis/filter/chainable_set_base.py
solvis/filter/parent_fault_id_filter.py
solvis/filter/rupture_id_filter.py
solvis/filter/subsection_id_filter.py
solvis/geometry.py
solvis/get_secret.py
solvis/scripts/cli.py
solvis/solution/__init__.py
solvis/solution/composite_solution.py
solvis/solution/dataframe_models.py
solvis/solution/fault_system_solution/__init__.py
solvis/solution/fault_system_solution/fault_system_solution.py
solvis/solution/fault_system_solution/fault_system_solution_file.py
solvis/solution/fault_system_solution/fault_system_solution_model.py
solvis/solution/inversion_solution/__init__.py
solvis/solution/inversion_solution/inversion_solution.py
solvis/solution/inversion_solution/inversion_solution_file.py
solvis/solution/inversion_solution/inversion_solution_model.py
solvis/solution/named_fault.py
solvis/solution/solution_participation.py
solvis/solution/solution_surfaces_builder.py
solvis/solution/typing.py
solvis/utils.py
solvis-1.3.1.dist-info/METADATA
solvis-1.3.1.dist-info/WHEEL
solvis-1.3.1.dist-info/entry_points.txt
solvis-1.3.1.dist-info/licenses/LICENSE
solvis-1.3.1.dist-info/RECORD
