Metadata-Version: 2.4
Name: solvis
Version: 1.3.1
Summary: Analysis of opensha modular solution files.
License-Expression: AGPL-3.0-or-later
License-File: LICENSE
Author: Chris B Chamberlain
Author-email: chrisbc@artisan.co.nz
Requires-Python: >=3.10,<4.0
Classifier: Programming Language :: Python :: 3
Classifier: Programming Language :: Python :: 3.10
Classifier: Programming Language :: Python :: 3.11
Classifier: Programming Language :: Python :: 3.12
Classifier: Programming Language :: Python :: 3.13
Classifier: Programming Language :: Python :: 3.14
Provides-Extra: demo
Provides-Extra: vtk
Requires-Dist: geopandas (>=1.0.1)
Requires-Dist: nzshm-common (>=0.8.1)
Requires-Dist: nzshm-model (>=0.13.5)
Requires-Dist: pandas (>=2.3.0)
Requires-Dist: pandera (>=0.26.0)
Requires-Dist: pyproj (>=3.3)
Requires-Dist: python-dateutil (>=2.8.2)
Requires-Dist: pytz (>=2025.1)
Requires-Dist: pyvista (>=0.44.1) ; extra == "vtk"
Requires-Dist: shapely ; extra == "demo"
